CHANGELOG
LICENSE
MANIFEST.in
README.rst
setup.py
django_light_draft.egg-info/PKG-INFO
django_light_draft.egg-info/SOURCES.txt
django_light_draft.egg-info/dependency_links.txt
django_light_draft.egg-info/requires.txt
django_light_draft.egg-info/top_level.txt
light_draft/__init__.py
light_draft/admin.py
light_draft/exceptions.py
light_draft/settings.py
light_draft/utils.py
light_draft/views.py
light_draft/management/__init__.py
light_draft/management/commands/__init__.py
light_draft/management/commands/drafts_remove.py
light_draft/static/admin/light.draft.js